michael960lib/__init__.py
michael960lib/common.py
michael960lib/dataman.py
michael960lib/double_well/__init__.py
michael960lib/double_well/defin.py
michael960lib/double_well/instances.py
michael960lib/double_well/multi_param.py
michael960lib/double_well/solver.py
michael960lib/double_well/two_param.py
michael960lib/file_util/__init__.py
michael960lib/file_util/data.py
michael960lib/file_util/path.py
michael960lib/file_util/remote.py
michael960lib/hard_sphere/__init__.py
michael960lib/hard_sphere/dummy.py
michael960lib/hard_sphere/property.py
michael960lib/hard_sphere/solver.py
michael960lib/lattice/__init__.py
michael960lib/lattice/structure.py
michael960lib/lattice/utility.py
michael960lib/math/__init__.py
michael960lib/math/analytic_function.py
michael960lib/math/fitting.py
michael960lib/math/fourier.py
michael960lib/math/general.py
michael960lib/math/hyperbolic_tangent.py
michael960lib/math/integration.py
michael960lib/math/ode.py
michael960lib/plotting/__init__.py
michael960lib/plotting/plot_helper.py
michael960lib/remote/__init__.py
michael960lib/remote/data_manager.py
michael960lib/remote/grile_interface.py
michael960lib/remote/logging.py
michael960lib/remote/remote.py
michael960_lib-0.1.4.dist-info/LICENSE
michael960_lib-0.1.4.dist-info/METADATA
michael960_lib-0.1.4.dist-info/WHEEL
michael960_lib-0.1.4.dist-info/top_level.txt
michael960_lib-0.1.4.dist-info/RECORD
