Metadata-Version: 2.1
Name: michael960-lib
Version: 0.1.4
Summary: base library for other packages by michael
Home-page: https://github.com/michael-960/michael960-lib
Author: Michael Wang
Author-email: mike.wang96029@gmail.com
Project-URL: Bug Tracker, https://github.com/michael-960/michael960-lib/issues
Classifier: Programming Language :: Python :: 3
Classifier: License :: OSI Approved :: MIT License
Classifier: Operating System :: OS Independent
Requires-Python: >=3.7
License-File: LICENSE
Requires-Dist: numpy (>=1.21.2)
Requires-Dist: scipy (>=1.7)
Requires-Dist: pyfftw (>=0.12.0)
Requires-Dist: matplotlib (>=3.5.1)
Requires-Dist: ujson (>=4)
